transliteration_brute_forcer/__init__.py
transliteration_brute_forcer-0.0.1.dist-info/METADATA
transliteration_brute_forcer-0.0.1.dist-info/WHEEL
transliteration_brute_forcer-0.0.1.dist-info/top_level.txt
transliteration_brute_forcer-0.0.1.dist-info/RECORD
