Metadata-Version: 2.1
Name: transliteration-brute-forcer
Version: 0.0.1
Summary: UNKNOWN
Home-page: https://github.com/GinTR1k/Transliteration-BruteForcer
Author: Alexander Karateev
Author-email: administrator@gintr1k.space
License: MIT
Platform: UNKNOWN
Classifier: License :: OSI Approved :: MIT License
Classifier: Development Status :: 3 - Alpha
Classifier: Programming Language :: Python
Classifier: Programming Language :: Python :: 3
Classifier: Programming Language :: Python :: 3.5
Classifier: Programming Language :: Python :: 3.6
Classifier: Programming Language :: Python :: 3.7
Classifier: Programming Language :: Python :: 3.8
Classifier: Programming Language :: Python :: 3.9
Classifier: Intended Audience :: Developers
Classifier: Topic :: Software Development
Classifier: Topic :: Software Development :: Libraries
